imaginairy_normal_map/__init__.py
imaginairy_normal_map/decoder.py
imaginairy_normal_map/encoder.py
imaginairy_normal_map/model.py
imaginairy_normal_map/submodules.py
imaginairy_normal_map/utils.py
imaginairy_normal_map-0.0.3.dist-info/LICENSE
imaginairy_normal_map-0.0.3.dist-info/METADATA
imaginairy_normal_map-0.0.3.dist-info/WHEEL
imaginairy_normal_map-0.0.3.dist-info/top_level.txt
imaginairy_normal_map-0.0.3.dist-info/RECORD
